setup.py
sirivasv_distributions/Binomialdistribution.py
sirivasv_distributions/Gaussiandistribution.py
sirivasv_distributions/Generaldistribution.py
sirivasv_distributions/__init__.py
sirivasv_distributions.egg-info/PKG-INFO
sirivasv_distributions.egg-info/SOURCES.txt
sirivasv_distributions.egg-info/dependency_links.txt
sirivasv_distributions.egg-info/not-zip-safe
sirivasv_distributions.egg-info/top_level.txt