Metadata-Version: 1.0
Name: sirivasv-distributions
Version: 0.1
Summary: Gaussian distributions
Home-page: UNKNOWN
Author: Saul Ivan Rivas Vega
Author-email: saul.ivan.rivas.vega@gmail.com
License: UNKNOWN
Platform: UNKNOWN
